concordancer/__init__.py
concordancer/concordancer.py
concordancer/demo.py
concordancer/indexedCorpus.py
concordancer/kwic_print.py
concordancer/server.py
concordancer/utils.py
concordancer-0.1.16.dist-info/METADATA
concordancer-0.1.16.dist-info/WHEEL
concordancer-0.1.16.dist-info/top_level.txt
concordancer-0.1.16.dist-info/RECORD
