Metadata-Version: 2.1
Name: concordancer
Version: 0.1.16
Summary: Extract concordance lines from corpus with CQL
Home-page: http://github.com/liao961120/concordancer
Author: Yongfu Liao
Author-email: liao961120@github.com
License: MIT
Requires-Dist: cqls
Requires-Dist: tabulate
Requires-Dist: falcon
Requires-Dist: falcon-cors
